setup.py
nctf_2019_installme/__init__.py
nctf_2019_installme.egg-info/PKG-INFO
nctf_2019_installme.egg-info/SOURCES.txt
nctf_2019_installme.egg-info/dependency_links.txt
nctf_2019_installme.egg-info/top_level.txt