Metadata-Version: 1.0
Name: nctf-2019-installme
Version: 0.2
Summary: Get flagggggggggg!
Home-page: http://www.google.com
Author: rmb122
Author-email: abuse@anti-spam.cn
License: GPLv3.0
Keywords: nctf,getflag
Platform: all
